prody/__init__.py
prody/apps/__init__.py
prody/apps/apptools.py
prody/apps/evol_apps/__init__.py
prody/apps/evol_apps/evol_coevol.py
prody/apps/evol_apps/evol_conserv.py
prody/apps/evol_apps/evol_fetch.py
prody/apps/evol_apps/evol_filter.py
prody/apps/evol_apps/evol_merge.py
prody/apps/evol_apps/evol_occupancy.py
prody/apps/evol_apps/evol_rankorder.py
prody/apps/evol_apps/evol_refine.py
prody/apps/evol_apps/evol_search.py
prody/apps/prody_apps/__init__.py
prody/apps/prody_apps/nmaoptions.py
prody/apps/prody_apps/prody_align.py
prody/apps/prody_apps/prody_anm.py
prody/apps/prody_apps/prody_biomol.py
prody/apps/prody_apps/prody_blast.py
prody/apps/prody_apps/prody_catdcd.py
prody/apps/prody_apps/prody_clustenm.py
prody/apps/prody_apps/prody_contacts.py
prody/apps/prody_apps/prody_eda.py
prody/apps/prody_apps/prody_energy.py
prody/apps/prody_apps/prody_fetch.py
prody/apps/prody_apps/prody_gnm.py
prody/apps/prody_apps/prody_pca.py
prody/apps/prody_apps/prody_select.py
prody/atomic/__init__.py
prody/atomic/acceptor.py
prody/atomic/angle.py
prody/atomic/atom.py
prody/atomic/atomgroup.py
prody/atomic/atomic.py
prody/atomic/atommap.py
prody/atomic/bond.py
prody/atomic/chain.py
prody/atomic/crossterm.py
prody/atomic/dihedral.py
prody/atomic/donor.py
prody/atomic/fields.py
prody/atomic/flags.py
prody/atomic/functions.py
prody/atomic/hierview.py
prody/atomic/improper.py
prody/atomic/nbexclusion.py
prody/atomic/pointer.py
prody/atomic/residue.py
prody/atomic/segment.py
prody/atomic/select.py
prody/atomic/selection.py
prody/atomic/subset.py
prody/chromatin/__init__.py
prody/chromatin/cluster.py
prody/chromatin/functions.py
prody/chromatin/hic.py
prody/chromatin/norm.py
prody/chromatin/straw.py
prody/compounds/__init__.py
prody/compounds/bird.py
prody/compounds/ccd.py
prody/compounds/functions.py
prody/compounds/pdbligands.py
prody/database/__init__.py
prody/database/cath.py
prody/database/dali.py
prody/database/goa.py
prody/database/pfam.py
prody/database/quartataweb.py
ProDy-2.4.1.dist-info/LICENSE.rst
ProDy-2.4.1.dist-info/METADATA
ProDy-2.4.1.dist-info/WHEEL
ProDy-2.4.1.dist-info/entry_points.txt
ProDy-2.4.1.dist-info/top_level.txt
ProDy-2.4.1.dist-info/RECORD
