Metadata-Version: 2.1
Name: ProDy
Version: 2.4.1
Summary: A Python Package for Protein Dynamics Analysis
Home-page: http://www.csb.pitt.edu/ProDy
Author: James Krieger, She Zhang, Hongchun Li, Cihan Kaya, Ahmet Bakan, and others
Author-email: kriegerj@pitt.edu
License: MIT License
Keywords: protein,dynamics,elastic network model,Gaussian network model,anisotropic network model,essential dynamics analysis,principal component analysis,Protein Data Bank,PDB,GNM,ANM,SM,PCA
Classifier: Development Status :: 5 - Production/Stable
Classifier: Intended Audience :: Education
Classifier: Intended Audience :: Science/Research
Classifier: License :: OSI Approved :: MIT License
Classifier: Operating System :: MacOS
Classifier: Operating System :: Microsoft :: Windows
Classifier: Operating System :: POSIX
Classifier: Programming Language :: Python
Classifier: Programming Language :: Python :: 2
Classifier: Programming Language :: Python :: 3
Classifier: Topic :: Scientific/Engineering :: Bio-Informatics
Classifier: Topic :: Scientific/Engineering :: Chemistry
License-File: LICENSE.rst
Requires-Dist: numpy (<1.24,>=1.10)
Requires-Dist: biopython (<=1.79)
Requires-Dist: pyparsing
Requires-Dist: scipy
Requires-Dist: setuptools
